wattameter-0.8.0.dist-info/METADATA
wattameter-0.8.0.dist-info/WHEEL
wattameter-0.8.0.dist-info/entry_points.txt
wattameter-0.8.0.dist-info/licenses/LICENSE
wattameter/__init__.py
wattameter/benchmark/README.md
wattameter/benchmark/__init__.py
wattameter/benchmark/overhead.py
wattameter/benchmark/update_time.py
wattameter/benchmark/utils.py
wattameter/cli/__init__.py
wattameter/cli/main.py
wattameter/cli/utils.py
wattameter/readers/__init__.py
wattameter/readers/base.py
wattameter/readers/nvml.py
wattameter/readers/rapl.py
wattameter/readers/utils.py
wattameter/tracker.py
wattameter/utils/__init__.py
wattameter/utils/postprocessing.py
wattameter/utils/slurm.sh
wattameter/utils/wattameter.sh
wattameter/utils/wattawait.sh
wattameter-0.8.0.dist-info/RECORD
