Metadata-Version: 2.1
Name: wattameter
Version: 0.8.0
Summary: Python package for monitoring and recording power usage, energy consumption, and performance metrics from hardware components such as GPUs and CPUs
Keywords: power-monitoring,energy-tracking,gpu-monitoring,cpu-monitoring,nvidia-ml,rapl,hpc,performance-monitoring
Author-Email: Weslley da Silva Pereira <wdasilv@nrel.gov>
License: BSD-3-Clause
Classifier: Intended Audience :: Science/Research
Classifier: Intended Audience :: Developers
Classifier: Intended Audience :: System Administrators
Classifier: Topic :: System :: Hardware
Classifier: Topic :: System :: Monitoring
Classifier: Topic :: Scientific/Engineering
Classifier: Topic :: Software Development :: Libraries :: Python Modules
Classifier: License :: OSI Approved :: BSD License
Classifier: Programming Language :: Python :: 3
Classifier: Programming Language :: Python :: 3.9
Classifier: Programming Language :: Python :: 3.10
Classifier: Programming Language :: Python :: 3.11
Classifier: Programming Language :: Python :: 3.12
Classifier: Operating System :: POSIX :: Linux
Classifier: Environment :: Console
Project-URL: Homepage, https://github.com/NREL/WattAMeter
Project-URL: Documentation, https://github.com/NREL/WattAMeter#readme
Project-URL: Bug Reports, https://github.com/NREL/WattAMeter/issues
Project-URL: Changelog, https://github.com/NREL/WattAMeter/releases
Requires-Python: >=3.9
Requires-Dist: nvidia-ml-py
Provides-Extra: postprocessing
Requires-Dist: pandas; extra == "postprocessing"
